{
  "claim_boundary": "Fail-closed review of GD&T/FAI measurement rows; blank template rows are not inspection evidence.",
  "status": "blocked_no_fai_results",
  "fai_template": "mechanical/e1-phone/review/gdt-fai-template.csv",
  "expected_characteristic_count": 13,
  "required_evidence_class": "physical_fai_result",
  "template_evidence_class": "",
  "forbidden_evidence_classes": [
    "blank_template",
    "planning",
    "simulated",
    "simulated_fai_result_for_planning_not_release",
    "simulated_first_article_for_evt_planning_not_production_release"
  ],
  "observed_row_count": 13,
  "complete_result_count": 0,
  "blank_or_incomplete_characteristics": [
    "CRIT-001",
    "CRIT-002",
    "CRIT-003",
    "CRIT-004",
    "CRIT-005",
    "STACK-006",
    "STACK-007",
    "STACK-008",
    "STACK-009",
    "STACK-010",
    "STACK-011",
    "STACK-012",
    "STACK-013"
  ],
  "cases": [
    {
      "characteristic_id": "CRIT-001",
      "expected_characteristic": true,
      "evidence_class": "",
      "evidence_class_allowed": false,
      "required_evidence_artifacts": [
        "fai_cmm_or_optical_raw_report",
        "inspection_equipment_calibration_certificate",
        "feature_inspection_photo_or_scan",
        "part_revision_tooling_and_resin_lot_records"
      ],
      "raw_measurement_artifact_present": false,
      "inspection_equipment_calibration_certificate_present": false,
      "inspection_photo_or_scan_present": false,
      "lot_traceability_record_present": false,
      "sample_id_present": false,
      "measured_value_present": false,
      "inspector_present": false,
      "declared_pass": false,
      "numeric_check_pass": true,
      "pass": false
    },
    {
      "characteristic_id": "CRIT-002",
      "expected_characteristic": true,
      "evidence_class": "",
      "evidence_class_allowed": false,
      "required_evidence_artifacts": [
        "fai_cmm_or_optical_raw_report",
        "inspection_equipment_calibration_certificate",
        "feature_inspection_photo_or_scan",
        "part_revision_tooling_and_resin_lot_records"
      ],
      "raw_measurement_artifact_present": false,
      "inspection_equipment_calibration_certificate_present": false,
      "inspection_photo_or_scan_present": false,
      "lot_traceability_record_present": false,
      "sample_id_present": false,
      "measured_value_present": false,
      "inspector_present": false,
      "declared_pass": false,
      "numeric_check_pass": true,
      "pass": false
    },
    {
      "characteristic_id": "CRIT-003",
      "expected_characteristic": true,
      "evidence_class": "",
      "evidence_class_allowed": false,
      "required_evidence_artifacts": [
        "fai_cmm_or_optical_raw_report",
        "inspection_equipment_calibration_certificate",
        "feature_inspection_photo_or_scan",
        "part_revision_tooling_and_resin_lot_records"
      ],
      "raw_measurement_artifact_present": false,
      "inspection_equipment_calibration_certificate_present": false,
      "inspection_photo_or_scan_present": false,
      "lot_traceability_record_present": false,
      "sample_id_present": false,
      "measured_value_present": false,
      "inspector_present": false,
      "declared_pass": false,
      "numeric_check_pass": true,
      "pass": false
    },
    {
      "characteristic_id": "CRIT-004",
      "expected_characteristic": true,
      "evidence_class": "",
      "evidence_class_allowed": false,
      "required_evidence_artifacts": [
        "fai_cmm_or_optical_raw_report",
        "inspection_equipment_calibration_certificate",
        "feature_inspection_photo_or_scan",
        "part_revision_tooling_and_resin_lot_records"
      ],
      "raw_measurement_artifact_present": false,
      "inspection_equipment_calibration_certificate_present": false,
      "inspection_photo_or_scan_present": false,
      "lot_traceability_record_present": false,
      "sample_id_present": false,
      "measured_value_present": false,
      "inspector_present": false,
      "declared_pass": false,
      "numeric_check_pass": true,
      "pass": false
    },
    {
      "characteristic_id": "CRIT-005",
      "expected_characteristic": true,
      "evidence_class": "",
      "evidence_class_allowed": false,
      "required_evidence_artifacts": [
        "fai_cmm_or_optical_raw_report",
        "inspection_equipment_calibration_certificate",
        "feature_inspection_photo_or_scan",
        "part_revision_tooling_and_resin_lot_records"
      ],
      "raw_measurement_artifact_present": false,
      "inspection_equipment_calibration_certificate_present": false,
      "inspection_photo_or_scan_present": false,
      "lot_traceability_record_present": false,
      "sample_id_present": false,
      "measured_value_present": false,
      "inspector_present": false,
      "declared_pass": false,
      "numeric_check_pass": true,
      "pass": false
    },
    {
      "characteristic_id": "STACK-006",
      "expected_characteristic": true,
      "evidence_class": "",
      "evidence_class_allowed": false,
      "required_evidence_artifacts": [
        "fai_stack_measurement_raw_report",
        "inspection_fixture_or_cmm_calibration_certificate",
        "assembly_stack_inspection_photo",
        "part_revision_tooling_and_resin_lot_records"
      ],
      "raw_measurement_artifact_present": false,
      "inspection_equipment_calibration_certificate_present": false,
      "inspection_photo_or_scan_present": false,
      "lot_traceability_record_present": false,
      "sample_id_present": false,
      "measured_value_present": false,
      "inspector_present": false,
      "declared_pass": false,
      "numeric_check_pass": true,
      "pass": false
    },
    {
      "characteristic_id": "STACK-007",
      "expected_characteristic": true,
      "evidence_class": "",
      "evidence_class_allowed": false,
      "required_evidence_artifacts": [
        "fai_stack_measurement_raw_report",
        "inspection_fixture_or_cmm_calibration_certificate",
        "assembly_stack_inspection_photo",
        "part_revision_tooling_and_resin_lot_records"
      ],
      "raw_measurement_artifact_present": false,
      "inspection_equipment_calibration_certificate_present": false,
      "inspection_photo_or_scan_present": false,
      "lot_traceability_record_present": false,
      "sample_id_present": false,
      "measured_value_present": false,
      "inspector_present": false,
      "declared_pass": false,
      "numeric_check_pass": true,
      "pass": false
    },
    {
      "characteristic_id": "STACK-008",
      "expected_characteristic": true,
      "evidence_class": "",
      "evidence_class_allowed": false,
      "required_evidence_artifacts": [
        "fai_stack_measurement_raw_report",
        "inspection_fixture_or_cmm_calibration_certificate",
        "assembly_stack_inspection_photo",
        "part_revision_tooling_and_resin_lot_records"
      ],
      "raw_measurement_artifact_present": false,
      "inspection_equipment_calibration_certificate_present": false,
      "inspection_photo_or_scan_present": false,
      "lot_traceability_record_present": false,
      "sample_id_present": false,
      "measured_value_present": false,
      "inspector_present": false,
      "declared_pass": false,
      "numeric_check_pass": true,
      "pass": false
    },
    {
      "characteristic_id": "STACK-009",
      "expected_characteristic": true,
      "evidence_class": "",
      "evidence_class_allowed": false,
      "required_evidence_artifacts": [
        "fai_stack_measurement_raw_report",
        "inspection_fixture_or_cmm_calibration_certificate",
        "assembly_stack_inspection_photo",
        "part_revision_tooling_and_resin_lot_records"
      ],
      "raw_measurement_artifact_present": false,
      "inspection_equipment_calibration_certificate_present": false,
      "inspection_photo_or_scan_present": false,
      "lot_traceability_record_present": false,
      "sample_id_present": false,
      "measured_value_present": false,
      "inspector_present": false,
      "declared_pass": false,
      "numeric_check_pass": true,
      "pass": false
    },
    {
      "characteristic_id": "STACK-010",
      "expected_characteristic": true,
      "evidence_class": "",
      "evidence_class_allowed": false,
      "required_evidence_artifacts": [
        "fai_stack_measurement_raw_report",
        "inspection_fixture_or_cmm_calibration_certificate",
        "assembly_stack_inspection_photo",
        "part_revision_tooling_and_resin_lot_records"
      ],
      "raw_measurement_artifact_present": false,
      "inspection_equipment_calibration_certificate_present": false,
      "inspection_photo_or_scan_present": false,
      "lot_traceability_record_present": false,
      "sample_id_present": false,
      "measured_value_present": false,
      "inspector_present": false,
      "declared_pass": false,
      "numeric_check_pass": true,
      "pass": false
    },
    {
      "characteristic_id": "STACK-011",
      "expected_characteristic": true,
      "evidence_class": "",
      "evidence_class_allowed": false,
      "required_evidence_artifacts": [
        "fai_stack_measurement_raw_report",
        "inspection_fixture_or_cmm_calibration_certificate",
        "assembly_stack_inspection_photo",
        "part_revision_tooling_and_resin_lot_records"
      ],
      "raw_measurement_artifact_present": false,
      "inspection_equipment_calibration_certificate_present": false,
      "inspection_photo_or_scan_present": false,
      "lot_traceability_record_present": false,
      "sample_id_present": false,
      "measured_value_present": false,
      "inspector_present": false,
      "declared_pass": false,
      "numeric_check_pass": true,
      "pass": false
    },
    {
      "characteristic_id": "STACK-012",
      "expected_characteristic": true,
      "evidence_class": "",
      "evidence_class_allowed": false,
      "required_evidence_artifacts": [
        "fai_stack_measurement_raw_report",
        "inspection_fixture_or_cmm_calibration_certificate",
        "assembly_stack_inspection_photo",
        "part_revision_tooling_and_resin_lot_records"
      ],
      "raw_measurement_artifact_present": false,
      "inspection_equipment_calibration_certificate_present": false,
      "inspection_photo_or_scan_present": false,
      "lot_traceability_record_present": false,
      "sample_id_present": false,
      "measured_value_present": false,
      "inspector_present": false,
      "declared_pass": false,
      "numeric_check_pass": true,
      "pass": false
    },
    {
      "characteristic_id": "STACK-013",
      "expected_characteristic": true,
      "evidence_class": "",
      "evidence_class_allowed": false,
      "required_evidence_artifacts": [
        "fai_stack_measurement_raw_report",
        "inspection_fixture_or_cmm_calibration_certificate",
        "assembly_stack_inspection_photo",
        "part_revision_tooling_and_resin_lot_records"
      ],
      "raw_measurement_artifact_present": false,
      "inspection_equipment_calibration_certificate_present": false,
      "inspection_photo_or_scan_present": false,
      "lot_traceability_record_present": false,
      "sample_id_present": false,
      "measured_value_present": false,
      "inspector_present": false,
      "declared_pass": false,
      "numeric_check_pass": true,
      "pass": false
    }
  ],
  "release_rule": "Every GD&T/FAI characteristic must include sample ID, measured value, inspector, passing disposition, evidence_class=physical_fai_result, raw CMM/inspection report, inspection equipment calibration certificate, inspection photo/scan, and part revision/tooling/resin lot traceability before tolerance release."
}
